novus/__init__.py
novus/asgi.py
novus/routers.py
novus/settings.py
novus/urls.py
novus/wsgi.py
your_python_sdk-0.1.dist-info/METADATA
your_python_sdk-0.1.dist-info/WHEEL
your_python_sdk-0.1.dist-info/top_level.txt
your_python_sdk-0.1.dist-info/RECORD
