Metadata-Version: 2.1
Name: your-python-sdk
Version: 0.1
Requires-Dist: requests
